djangocms_form_builder/__init__.py
djangocms_form_builder/actions.py
djangocms_form_builder/admin.py
djangocms_form_builder/apps.py
djangocms_form_builder/constants.py
djangocms_form_builder/entry_model.py
djangocms_form_builder/fields.py
djangocms_form_builder/forms.py
djangocms_form_builder/helpers.py
djangocms_form_builder/models.py
djangocms_form_builder/recaptcha.py
djangocms_form_builder/settings.py
djangocms_form_builder/urls.py
djangocms_form_builder/views.py
djangocms_form_builder/cms_plugins/__init__.py
djangocms_form_builder/cms_plugins/ajax_plugins.py
djangocms_form_builder/cms_plugins/form_plugins.py
djangocms_form_builder/cms_plugins/legacy.py
djangocms_form_builder/frontends/__init__.py
djangocms_form_builder/frontends/bootstrap5.py
djangocms_form_builder/frontends/foundation6.py
djangocms_form_builder/locale/de/LC_MESSAGES/django.mo
djangocms_form_builder/locale/de/LC_MESSAGES/django.po
djangocms_form_builder/locale/en/LC_MESSAGES/django.mo
djangocms_form_builder/locale/en/LC_MESSAGES/django.po
djangocms_form_builder/locale/nl/LC_MESSAGES/django.mo
djangocms_form_builder/locale/nl/LC_MESSAGES/django.po
djangocms_form_builder/locale/sq/LC_MESSAGES/django.mo
djangocms_form_builder/locale/sq/LC_MESSAGES/django.po
djangocms_form_builder/migrations/0001_initial.py
djangocms_form_builder/migrations/0002_alter_form_cmsplugin_ptr_and_more.py
djangocms_form_builder/migrations/0003_auto_20230129_1950.py
djangocms_form_builder/migrations/__init__.py
djangocms_form_builder/static/djangocms_form_builder/css/actions_form.css
djangocms_form_builder/static/djangocms_form_builder/css/button_group.css
djangocms_form_builder/static/djangocms_form_builder/js/actions_form.js
djangocms_form_builder/templates/captcha/includes/js_v2_checkbox.html
djangocms_form_builder/templates/captcha/includes/js_v2_invisible.html
djangocms_form_builder/templates/djangocms_form_builder/ajax_base.html
djangocms_form_builder/templates/djangocms_form_builder/ajax_form.html
djangocms_form_builder-0.3.2.dist-info/METADATA
djangocms_form_builder-0.3.2.dist-info/WHEEL
djangocms_form_builder-0.3.2.dist-info/licenses/LICENSE
djangocms_form_builder-0.3.2.dist-info/RECORD
