Metadata-Version: 2.4
Name: djangocms-form-builder
Version: 0.3.2
Summary: Adds a form editor to the structure board of django CMS.
Project-URL: Homepage, https://github.com/fsbraun/djangocms-form-builder
Author-email: fsbraun <fsbraun@gmx.de>
License: BSD-3-Clause
License-File: LICENSE
Classifier: Development Status :: 4 - Beta
Classifier: Environment :: Web Environment
Classifier: Framework :: Django
Classifier: Framework :: Django :: 4.2
Classifier: Framework :: Django :: 5.0
Classifier: Framework :: Django :: 5.1
Classifier: Framework :: Django CMS
Classifier: Framework :: Django CMS :: 3.9
Classifier: Framework :: Django CMS :: 3.10
Classifier: Framework :: Django CMS :: 3.11
Classifier: Framework :: Django CMS :: 4.0
Classifier: Framework :: Django CMS :: 4.1
Classifier: Intended Audience :: Developers
Classifier: License :: OSI Approved :: BSD License
Classifier: Operating System :: OS Independent
Classifier: Programming Language :: Python
Classifier: Programming Language :: Python :: 3
Classifier: Programming Language :: Python :: 3.9
Classifier: Programming Language :: Python :: 3.10
Classifier: Programming Language :: Python :: 3.11
Classifier: Programming Language :: Python :: 3.12
Classifier: Topic :: Internet :: WWW/HTTP
Classifier: Topic :: Internet :: WWW/HTTP :: Dynamic Content
Classifier: Topic :: Software Development
Classifier: Topic :: Software Development :: Libraries
Requires-Python: >=3.9
Requires-Dist: django-cms>=3.10
Requires-Dist: django-entangled
Requires-Dist: django>=3.2
Requires-Dist: djangocms-attributes-field>=1
Provides-Extra: recaptcha
Requires-Dist: django-recaptcha; extra == 'recaptcha'
